Metadata-Version: 2.1
Name: TSMtester
Version: 0.0.6
Summary: Traveling salesman problem for testing and benchmarking optimization algorithms
Home-page: https://github.com/Tommer-R/Traveling-salesman
Author: Tommer Rissin
Author-email: tommerrissin@gmail.com
License-File: LICENSE
